{
  "/__docusaurus/debug-89c": {
    "__comp": "__comp---theme-debug-config-23-a-2ff",
    "__context": {
      "plugin": "plugin---docusaurus-debug-4-c-9-31b"
    }
  },
  "/__docusaurus/debug/config-47a": {
    "__comp": "__comp---theme-debug-config-23-a-2ff",
    "__context": {
      "plugin": "plugin---docusaurus-debug-4-c-9-31b"
    }
  },
  "/__docusaurus/debug/content-8cd": {
    "__comp": "__comp---theme-debug-contentba-8-ce7",
    "__context": {
      "plugin": "plugin---docusaurus-debug-4-c-9-31b"
    },
    "allContent": "allContent---docusaurus-debug-content-246-9aa"
  },
  "/__docusaurus/debug/globalData-a43": {
    "__comp": "__comp---theme-debug-global-dataede-0fa",
    "__context": {
      "plugin": "plugin---docusaurus-debug-4-c-9-31b"
    }
  },
  "/__docusaurus/debug/metadata-f36": {
    "__comp": "__comp---theme-debug-site-metadata-68-e-3d4",
    "__context": {
      "plugin": "plugin---docusaurus-debug-4-c-9-31b"
    }
  },
  "/__docusaurus/debug/registry-ff5": {
    "__comp": "__comp---theme-debug-registry-679-501",
    "__context": {
      "plugin": "plugin---docusaurus-debug-4-c-9-31b"
    }
  },
  "/__docusaurus/debug/routes-f20": {
    "__comp": "__comp---theme-debug-routes-946-699",
    "__context": {
      "plugin": "plugin---docusaurus-debug-4-c-9-31b"
    }
  },
  "/blog-e2a": {
    "__comp": "__comp---theme-blog-list-pagea-6-a-7ba",
    "__context": {
      "plugin": "plugin---blog-509-130"
    },
    "sidebar": "sidebar---blog-814-8ac",
    "items": [
      {
        "content": "content---blog-766-e3c"
      },
      {
        "content": "content---blogf-4-f-cd7"
      },
      {
        "content": "content---blog-871-381"
      },
      {
        "content": "content---blog-925-e00"
      }
    ],
    "metadata": "metadata---blogb-2-b-df1"
  },
  "/blog/archive-d38": {
    "__comp": "__comp---theme-blog-archive-page-9-e-4-1d8",
    "__context": {
      "plugin": "plugin---blog-509-130"
    },
    "archive": "archive---blog-archiveb-2-f-393"
  },
  "/blog/first-blog-post-be7": {
    "__comp": "__comp---theme-blog-post-pageccc-cab",
    "__context": {
      "plugin": "plugin---blog-509-130"
    },
    "sidebar": "sidebar---blog-814-8ac",
    "content": "content---blog-first-blog-poste-27-4a1"
  },
  "/blog/long-blog-post-527": {
    "__comp": "__comp---theme-blog-post-pageccc-cab",
    "__context": {
      "plugin": "plugin---blog-509-130"
    },
    "sidebar": "sidebar---blog-814-8ac",
    "content": "content---blog-long-blog-post-736-bc7"
  },
  "/blog/mdx-blog-post-a32": {
    "__comp": "__comp---theme-blog-post-pageccc-cab",
    "__context": {
      "plugin": "plugin---blog-509-130"
    },
    "sidebar": "sidebar---blog-814-8ac",
    "content": "content---blog-mdx-blog-post-593-37b"
  },
  "/blog/tags-492": {
    "__comp": "__comp---theme-blog-tags-list-page-01-a-d0b",
    "__context": {
      "plugin": "plugin---blog-509-130"
    },
    "sidebar": "sidebar---blog-814-8ac",
    "tags": "tags---blog-tagsa-70-da2"
  },
  "/blog/tags/docusaurus-05e": {
    "__comp": "__comp---theme-blog-tags-posts-page-687-b6c",
    "__context": {
      "plugin": "plugin---blog-509-130"
    },
    "sidebar": "sidebar---blog-814-8ac",
    "items": [
      {
        "content": "content---blog-766-e3c"
      },
      {
        "content": "content---blogf-4-f-cd7"
      },
      {
        "content": "content---blog-871-381"
      },
      {
        "content": "content---blog-925-e00"
      }
    ],
    "tag": "tag---blog-tags-docusaurusa-80-728",
    "listMetadata": "listMetadata---blog-tags-docusaurus-608-c09"
  },
  "/blog/tags/facebook-ac3": {
    "__comp": "__comp---theme-blog-tags-posts-page-687-b6c",
    "__context": {
      "plugin": "plugin---blog-509-130"
    },
    "sidebar": "sidebar---blog-814-8ac",
    "items": [
      {
        "content": "content---blog-766-e3c"
      }
    ],
    "tag": "tag---blog-tags-facebook-031-c52",
    "listMetadata": "listMetadata---blog-tags-facebook-096-d31"
  },
  "/blog/tags/hello-11a": {
    "__comp": "__comp---theme-blog-tags-posts-page-687-b6c",
    "__context": {
      "plugin": "plugin---blog-509-130"
    },
    "sidebar": "sidebar---blog-814-8ac",
    "items": [
      {
        "content": "content---blog-766-e3c"
      },
      {
        "content": "content---blog-871-381"
      }
    ],
    "tag": "tag---blog-tags-hello-30-a-bed",
    "listMetadata": "listMetadata---blog-tags-hello-664-70a"
  },
  "/blog/tags/hola-7ad": {
    "__comp": "__comp---theme-blog-tags-posts-page-687-b6c",
    "__context": {
      "plugin": "plugin---blog-509-130"
    },
    "sidebar": "sidebar---blog-814-8ac",
    "items": [
      {
        "content": "content---blog-925-e00"
      }
    ],
    "tag": "tag---blog-tags-holae-16-18a",
    "listMetadata": "listMetadata---blog-tags-hola-4-c-9-a24"
  },
  "/blog/welcome-676": {
    "__comp": "__comp---theme-blog-post-pageccc-cab",
    "__context": {
      "plugin": "plugin---blog-509-130"
    },
    "sidebar": "sidebar---blog-814-8ac",
    "content": "content---blog-welcomed-9-f-ffb"
  },
  "/markdown-page-dde": {
    "__comp": "__comp---theme-mdx-page-1-f-3-b90",
    "__context": {
      "plugin": "plugin---markdown-paged-87-d4a"
    },
    "content": "content---markdown-page-393-028"
  },
  "/-935": {
    "__comp": "__comp---theme-doc-page-1-be-9be",
    "__context": {
      "plugin": "plugin---075-427"
    },
    "versionMetadata": "versionMetadata---935-fcf"
  },
  "/-96c": {
    "__comp": "__comp---theme-doc-item-178-a40",
    "content": "content---0-e-3-279"
  },
  "/category/contributing-guidelines-409": {
    "__comp": "__comp---theme-doc-category-generated-index-page-14-e-640",
    "categoryGeneratedIndex": "categoryGeneratedIndex---category-contributing-guidelines-2-e-7-3fe"
  },
  "/category/open-source-349": {
    "__comp": "__comp---theme-doc-category-generated-index-page-14-e-640",
    "categoryGeneratedIndex": "categoryGeneratedIndex---category-open-source-842-4f1"
  },
  "/contributing-guidelines/deploy-your-site-d19": {
    "__comp": "__comp---theme-doc-item-178-a40",
    "content": "content---contributing-guidelines-deploy-your-sitef-88-21b"
  },
  "/open-source/manage-docs-versions-a6e": {
    "__comp": "__comp---theme-doc-item-178-a40",
    "content": "content---open-source-manage-docs-versionsa-0-a-85a"
  },
  "/open-source/translate-your-site-530": {
    "__comp": "__comp---theme-doc-item-178-a40",
    "content": "content---open-source-translate-your-sitef-1-a-6a3"
  }
}